README.md
setup.cfg
setup.py
easyhid/__init__.py
easyhid/easyhid.py
easyhid/version.py
easyhid.egg-info/PKG-INFO
easyhid.egg-info/SOURCES.txt
easyhid.egg-info/dependency_links.txt
easyhid.egg-info/not-zip-safe
easyhid.egg-info/requires.txt
easyhid.egg-info/top_level.txt