Metadata-Version: 1.0
Name: easyhid
Version: 0.0.7
Summary: A simple interface to the HIDAPI library.
Home-page: http://github.com/ahtn/python-easyhid
Author: jem
Author-email: jem@seethis.link
License: MIT
Keywords: hidapi,usb,hid
Platform: UNKNOWN
